README.md
setup.py
py_dist/Binomial.py
py_dist/Gaussian.py
py_dist/General.py
py_dist/__init__.py
py_dist/example.py
py_dist/test.py
py_dist.egg-info/PKG-INFO
py_dist.egg-info/SOURCES.txt
py_dist.egg-info/dependency_links.txt
py_dist.egg-info/not-zip-safe
py_dist.egg-info/top_level.txt