Metadata-Version: 2.1
Name: py-dist
Version: 0.1
Summary: Gaussian and Binomial distributions
Home-page: UNKNOWN
Author: Thuy Trinh
Author-email: thuytrinht4@gmail.com
License: UNKNOWN
Platform: UNKNOWN
